test_toolbox/__init__.py
test_toolbox/bdd.py
test_toolbox/helpers.py
test_toolbox/output.py
test_toolbox/spy.py
TestToolbox-0.1.1.dist-info/LICENSE
TestToolbox-0.1.1.dist-info/METADATA
TestToolbox-0.1.1.dist-info/WHEEL
TestToolbox-0.1.1.dist-info/top_level.txt
TestToolbox-0.1.1.dist-info/RECORD
