Metadata-Version: 2.1
Name: TestToolbox
Version: 0.1.1
Summary: Tools and extensions for testing in Python.
Home-page: https://github.com/cope-systems/test_toolbox
Author: Robert Cope
Author-email: robert@copesystems.com
License: BSD
Platform: any
Classifier: Development Status :: 3 - Alpha
Classifier: Topic :: Utilities
Classifier: Topic :: Software Development :: Testing
Classifier: License :: OSI Approved :: BSD License
